custlib/__init__.py
custlib/classlib.py
custlib-0.1.0.dist-info/METADATA
custlib-0.1.0.dist-info/WHEEL
custlib-0.1.0.dist-info/top_level.txt
custlib-0.1.0.dist-info/RECORD
