Metadata-Version: 2.1
Name: custlib
Version: 0.1.0
Summary: My first Python library
Home-page: UNKNOWN
Author: Me
License: MIT
Platform: UNKNOWN
